algebraIberoIA/__init__.py
algebraIberoIA/ibero_al.py
algebraiberoia-0.0.3.dist-info/METADATA
algebraiberoia-0.0.3.dist-info/WHEEL
algebraiberoia-0.0.3.dist-info/RECORD
