Metadata-Version: 2.1
Name: algebraIberoIA
Version: 0.0.3
Summary: CoAutor: Santiago Romo Rubio, Libreria de algebra lineal
Project-URL: Homepage, https://github.com/0mudkip/repo_paquete_ibero_al
Project-URL: Bug Tracker, https://github.com/0mudkip/repo_paquete_ibero_al/issues
Author-email: Edgar Ivan Gálvez Ortega <kasito321@gmail.com>
Classifier: License :: OSI Approved :: MIT License
Classifier: Operating System :: OS Independent
Classifier: Programming Language :: Python :: 3
Requires-Python: >=3.7
Requires-Dist: matplotlib==3.8.1
Requires-Dist: numpy==1.26.0
Requires-Dist: scipy==1.11.3
